cmon_net/__init__.py
cmon_net/cmon_net.py
cmon_net-0.1.0.dist-info/LICENSE
cmon_net-0.1.0.dist-info/METADATA
cmon_net-0.1.0.dist-info/WHEEL
cmon_net-0.1.0.dist-info/entry_points.txt
cmon_net-0.1.0.dist-info/RECORD
